{
    "meta": {
        "portal_name": "perl",
        "language": "fr",
        "updated": "20150507"
    },
    "schema": {
        "html:portal": "http://fr.recuweb.com/perl/",
        "graph:videos": "http://fr.recuweb.com/graph/v1.0/perl/perl/vid%C3%A9os.json",
        "graph:news": "http://fr.recuweb.com/graph/v1.0/perl/perl/actualit%C3%A9s.json",
        "graph:blogs": "http://fr.recuweb.com/graph/v1.0/perl/perl/blogs.json"
    },
    "items": {
        "youtube.com/2015/03/d%C3%A9couverte-de-perl-5-trailer": {
            "title": "D\u00e9couverte de Perl 5 - trailer...",
            "snippet": "D\u00e9couverte de Perl 5 - trailer Formation compl\u00e8te: Apprenez \u00e0 d\u00e9velopper des scripts et des applications compl\u00e8tes avec Perl Perl est un langage de script tr\u00e8s populaire car tr\u00e8s puissant et... From: monvideo2brain Views: 25 0 ratings Time:...",
            "date": "2015-03-27",
            "author_name": "monvideo2brain",
            "categories": "perl,langage",
            "tags": "perl,d\u00e9couverte",
            "recuweb_url": "http://fr.recuweb.com/langage/youtube.com/2015/03/d%C3%A9couverte-de-perl-5-trailer",
            "resource_url": "http://gdata.youtube.com/feeds/base/videos?max-results=50&start-index=1&client=ytapi-youtube-search&v=2&q=perl&hl=fr-FR&lang=fr&lr=fr&orderby=relevance_lang_fr",
            "source_url": "http://youtube.com/watch?v=lIkql5ysnWM&feature=youtube_gdata",
            "img_url": "http://img.youtube.com/vi/lIkql5ysnWM/0.jpg"
        },
        "youtube.com/2015/03/haul-allemagne-1-catrice-et-essence-au-dm-de-perl": {
            "title": "haul Allemagne 1: Haul Catrice et Essence au DM de Perl...",
            "snippet": "haul Allemagne 1: Haul Catrice et Essence au DM de Perl Mes Vid\u00e9os de Hauls Beaut\u00e9/Maquillage,Tutoriels, Revues/Avis et Swatches palettes et d\u00e9couverte de bons plans. Suivez Mes achats Action/Tati/Cor\u00e9en/Neve Cosmetics/Urban Decay/Sephora...",
            "date": "2015-03-11",
            "author_name": "la vie en rose",
            "categories": "perl",
            "tags": "d\u00e9couverte,perl",
            "recuweb_url": "http://fr.recuweb.com/perl/youtube.com/2015/03/haul-allemagne-1-catrice-et-essence-au-dm-de-perl",
            "resource_url": "http://gdata.youtube.com/feeds/base/videos?max-results=50&start-index=1&client=ytapi-youtube-search&v=2&q=perl&hl=fr-FR&lang=fr&lr=fr&orderby=relevance_lang_fr",
            "source_url": "http://youtube.com/watch?v=5l3qInsBo7s&feature=youtube_gdata",
            "img_url": "http://img.youtube.com/vi/5l3qInsBo7s/0.jpg"
        },
        "youtube.com/2015/03/nou-l-amour-risess-group-perl-crew": {
            "title": "Nou L'amour Nou Risess.... Group Perl Crew...",
            "snippet": "Nou L'amour Nou Risess.... Group Perl Crew... Mo pe na ni Larzent ni lor pou donn twa. me selma nou L'amour Grandi tou lezour..... Aut/comp/edit: Richard Perl.... Image De Jarsor Audio Vizuel....... From: Residu Jean Alain Views: 430 11 ratings...",
            "date": "2015-03-06",
            "author_name": "Residu Jean Alain",
            "categories": "perl",
            "tags": "perl",
            "recuweb_url": "http://fr.recuweb.com/perl/youtube.com/2015/03/nou-l-amour-risess-group-perl-crew",
            "resource_url": "http://gdata.youtube.com/feeds/base/videos?max-results=50&start-index=1&client=ytapi-youtube-search&v=2&q=perl&hl=fr-FR&lang=fr&lr=fr&orderby=relevance_lang_fr",
            "source_url": "http://youtube.com/watch?v=AZzoUf_272Q&feature=youtube_gdata",
            "img_url": "http://img.youtube.com/vi/AZzoUf_272Q/0.jpg"
        },
        "dailymotion.com/2015/02/exploit-huawei-0day-vulnerability-using-perl-coded-by-isdo213": {
            "title": "exploit huawei 0day vulnerability using perl coded by isdo213...",
            "snippet": "i don't need the opportunity to hack icreat the opportunity i'm dz exploiterAuthor: 3a9liadeuxTags: huawei perl isdo213 Posted: 22 February 2015Rating:: 0...",
            "date": "2015-02-22",
            "author_name": "3a9liadeux",
            "categories": "perl",
            "tags": "perl",
            "recuweb_url": "http://fr.recuweb.com/perl/dailymotion.com/2015/02/exploit-huawei-0day-vulnerability-using-perl-coded-by-isdo213",
            "resource_url": "http://www.dailymotion.com/rss/relevance/lang/fr/search/fr+localhost+com+perl/0?af=1",
            "source_url": "http://dailymotion.com/video/x2hup2x_exploit-huawei-0day-vulnerability-using-perl-coded-by-isdo213_tech",
            "img_url": "http://www.dailymotion.com/thumbnail/video/x2hup2x_exploit-huawei-0day-vulnerability-using-perl-coded-by-isdo213_tech"
        },
        "youtube.com/2015/02/le-s-play-pokemon-perl-edition-part-1-der-anfang": {
            "title": "Le's play Pokemon Perl Edition Part 1 der Anfang...",
            "snippet": "Le's play Pokemon Perl Edition Part 1 der Anfang From: Pascal Vicere Views: 72 4 ratings Time: 10:01 More in People & Blogs...",
            "date": "2015-02-11",
            "author_name": "Pascal Vicere",
            "categories": "perl,play",
            "tags": "perl,people",
            "recuweb_url": "http://fr.recuweb.com/play/youtube.com/2015/02/le-s-play-pokemon-perl-edition-part-1-der-anfang",
            "resource_url": "http://gdata.youtube.com/feeds/base/videos?max-results=50&start-index=1&client=ytapi-youtube-search&v=2&q=perl&hl=fr-FR&lang=fr&lr=fr&orderby=relevance_lang_fr",
            "source_url": "http://youtube.com/watch?v=_G8m-eGC60Y&feature=youtube_gdata",
            "img_url": "http://img.youtube.com/vi/_G8m-eGC60Y/0.jpg"
        },
        "youtube.com/2015/01/tuto-ddos-avec-un-vps-sous-linux-le-script-perl": {
            "title": "TUTO DDoS avec un VPS sous Linux le script Perl...",
            "snippet": "[TUTO] DDoS avec un VPS sous Linux le script Perl Le lien du code Perl (): L'H\u00e9bergeur VPS linux pas cher: From: - H33nok - Views: 259 8 ratings Time: 04:36 More in Gaming...",
            "date": "2015-01-31",
            "author_name": "\u3008-\u3009 H33nok \u3008-\u3009",
            "categories": "perl",
            "tags": "tuto,perl",
            "recuweb_url": "http://fr.recuweb.com/perl/youtube.com/2015/01/tuto-ddos-avec-un-vps-sous-linux-le-script-perl",
            "resource_url": "http://gdata.youtube.com/feeds/base/videos?max-results=50&start-index=1&client=ytapi-youtube-search&v=2&q=perl&hl=fr-FR&lang=fr&lr=fr&orderby=relevance_lang_fr",
            "source_url": "http://youtube.com/watch?v=cvRcZXqZVP0&feature=youtube_gdata",
            "img_url": "http://img.youtube.com/vi/cvRcZXqZVP0/0.jpg"
        },
        "youtube.com/2015/01/lc-vs-steel-co-qui-perl": {
            "title": "LC Vs Steel: CO-QUI-PERL...",
            "snippet": "LC Vs Steel: CO-QUI-PERL Salut \u00e0 tous et \u00e0 toutes c'est Cizayoxy pour une nouvelle vid\u00e9o. Aujourd'hui on se retrouve pour un match LC sur ROSA!! A partir de maintenant je prendrais mes matchs sur twitter donc go... From: Cizayoxy Views: 6641 186...",
            "date": "2015-01-25",
            "author_name": "Cizayoxy",
            "categories": "twitter,perl",
            "tags": "partir,perl",
            "recuweb_url": "http://fr.recuweb.com/perl/youtube.com/2015/01/lc-vs-steel-co-qui-perl",
            "resource_url": "http://gdata.youtube.com/feeds/base/videos?max-results=50&start-index=1&client=ytapi-youtube-search&v=2&q=perl&hl=fr-FR&lang=fr&lr=fr&orderby=relevance_lang_fr",
            "source_url": "http://youtube.com/watch?v=T227kJo98HU&feature=youtube_gdata",
            "img_url": "http://img.youtube.com/vi/T227kJo98HU/0.jpg"
        },
        "youtube.com/2014/12/jevouschouchoute-teste-les-magicperl-dans-la-cat%C3%A9gorie-arts-cr%C3%A9atifs": {
            "title": "jevouschouchoute teste les MagicPerl, dans la cat\u00e9gorie Arts Cr\u00e9atifs...",
            "snippet": "jevouschouchoute teste les MagicPerl, dans la cat\u00e9gorie Arts Cr\u00e9atifs les Magic Perl de Vivid sont une super occupation cr\u00e9ative pour les kids de jevouschouchoute. From: Sylvaine Cohen Views: 202 1 ratings Time: 02:44 More in People & Blogs...",
            "date": "2014-12-08",
            "author_name": "Sylvaine Cohen",
            "categories": "perl,arts",
            "tags": "magic,magic_perl,perl,people",
            "recuweb_url": "http://fr.recuweb.com/arts/youtube.com/2014/12/jevouschouchoute-teste-les-magicperl-dans-la-cat%C3%A9gorie-arts-cr%C3%A9atifs",
            "resource_url": "http://gdata.youtube.com/feeds/base/videos?max-results=50&start-index=1&client=ytapi-youtube-search&v=2&q=perl&hl=fr-FR&lang=fr&lr=fr&orderby=relevance_lang_fr",
            "source_url": "http://youtube.com/watch?v=bxa9h1MQXRs&feature=youtube_gdata",
            "img_url": "http://img.youtube.com/vi/bxa9h1MQXRs/0.jpg"
        },
        "youtube.com/2014/11/kit-de-d%C3%A9marrage-magic-perl-unboxing-et-tuto": {
            "title": "Kit de d\u00e9marrage Magic Perl (unboxing et tuto)...",
            "snippet": "Kit de d\u00e9marrage Magic Perl (unboxing et tuto) Destin\u00e9 aux enfants \u00e0 partir de 4 ans, le stylo \u00e0 perles Magic Perl'est facile \u00e0 utiliser. Il permet d'assembler les perles sans colle, sans chauffer et sans faire de tache. Erwan... From:...",
            "date": "2014-11-13",
            "author_name": "GenerationJOUETS",
            "categories": "perl",
            "tags": "partir,tuto,magic,magic_perl,perl",
            "recuweb_url": "http://fr.recuweb.com/perl/youtube.com/2014/11/kit-de-d%C3%A9marrage-magic-perl-unboxing-et-tuto",
            "resource_url": "http://gdata.youtube.com/feeds/base/videos?max-results=50&start-index=1&client=ytapi-youtube-search&v=2&q=perl&hl=fr-FR&lang=fr&lr=fr&orderby=relevance_lang_fr",
            "source_url": "http://youtube.com/watch?v=Jk1FDx0iWPM&feature=youtube_gdata",
            "img_url": "http://img.youtube.com/vi/Jk1FDx0iWPM/0.jpg"
        },
        "youtube.com/2014/08/pr%C3%A9sentation-de-l-%C3%A9cole-perl": {
            "title": "Pr\u00e9sentation de l'\u00e9cole PERL...",
            "snippet": "Pr\u00e9sentation de l'\u00e9cole PERL Vid\u00e9o r\u00e9alis\u00e9e par Marge Communication pour l'\u00e9cole PERL, \u00e9cole situ\u00e9e \u00e0 Paris proposant des cours de fran\u00e7ais pour les \u00e9trangers. From: Marge Communication Views: 50 0 ratings Time: 02:56 More in People &...",
            "date": "2014-08-28",
            "author_name": "Marge Communication",
            "categories": "perl",
            "tags": "perl,people",
            "recuweb_url": "http://fr.recuweb.com/perl/youtube.com/2014/08/pr%C3%A9sentation-de-l-%C3%A9cole-perl",
            "resource_url": "http://gdata.youtube.com/feeds/base/videos?max-results=50&start-index=1&client=ytapi-youtube-search&v=2&q=perl&hl=fr-FR&lang=fr&lr=fr&orderby=relevance_lang_fr",
            "source_url": "http://youtube.com/watch?v=_1stB_Uempc&feature=youtube_gdata",
            "img_url": "http://img.youtube.com/vi/_1stB_Uempc/0.jpg"
        }
    }
}