{
    "meta": {
        "portal_name": "mythologie",
        "language": "fr",
        "updated": "20150502"
    },
    "schema": {
        "html:portal": "http://fr.recuweb.com/mythologie/",
        "graph:videos": "http://fr.recuweb.com/graph/v1.0/mythologie/mythologie/vid%C3%A9os.json",
        "graph:news": "http://fr.recuweb.com/graph/v1.0/mythologie/mythologie/actualit%C3%A9s.json",
        "graph:blogs": "http://fr.recuweb.com/graph/v1.0/mythologie/mythologie/blogs.json"
    },
    "items": {
        "youtube.com/2014/12/la-mythologie-nordique-mythes-et-l%C3%A9gendes-2": {
            "title": "La mythologie nordique - Mythes et l\u00e9gendes 2...",
            "snippet": "La mythologie nordique - Mythes et l\u00e9gendes 2 Soutenez moi sur Tipeee: Abonnez-vous \u00e0 ma chaine: Facebook: Twitter:... From: Nota Bene Views: 140127 6993 ratings Time: 22:51 More in Education...",
            "date": "2014-12-29",
            "author_name": "Nota Bene",
            "categories": "mythologie,facebook,twitter",
            "tags": "nota,nota_bene,bene,chaine,moi,l\u00e9gendes,mythologie,mythologie-nordique,mythes,soutenez,tipeee,abonnez,facebook,twitter,education",
            "recuweb_url": "http://fr.recuweb.com/twitter/youtube.com/2014/12/la-mythologie-nordique-mythes-et-l%C3%A9gendes-2",
            "resource_url": "http://gdata.youtube.com/feeds/base/videos?max-results=50&start-index=1&client=ytapi-youtube-search&v=2&q=mythologie%2Bmythologie&hl=fr-FR&lang=fr&lr=fr&orderby=relevance_lang_fr",
            "source_url": "http://youtube.com/watch?v=SWEPb5KJffk&feature=youtube_gdata",
            "img_url": "http://img.youtube.com/vi/SWEPb5KJffk/0.jpg"
        },
        "youtube.com/2014/12/f%C3%A9loche-mythologie-hd-1080p": {
            "title": "F\u00e9loche - Mythologie - HD (1080p)...",
            "snippet": "F\u00e9loche - Mythologie - HD (1080p) \"Mythologie\" de F\u00e9loche feat. Rona Hartner Album: \"Silbo\" (2013) Paroles: \u00c7a m'a pris du temps pour arriver jusqu'\u00e0 toi \u00c7a m'a pris du temps pour arriver jusqu'\u00e0 toi J'ai d\u00fb quitter... From: AllMusicWorld...",
            "date": "2014-12-08",
            "author_name": "AllMusicWorld",
            "categories": "mythologie",
            "tags": "mythologie",
            "recuweb_url": "http://fr.recuweb.com/mythologie/youtube.com/2014/12/f%C3%A9loche-mythologie-hd-1080p",
            "resource_url": "http://gdata.youtube.com/feeds/base/videos?max-results=50&start-index=1&client=ytapi-youtube-search&v=2&q=mythologie%2Bmythologie&hl=fr-FR&lang=fr&lr=fr&orderby=relevance_lang_fr",
            "source_url": "http://youtube.com/watch?v=xTtl--bqEPM&feature=youtube_gdata",
            "img_url": "http://img.youtube.com/vi/xTtl--bqEPM/0.jpg"
        },
        "youtube.com/2014/12/mythologie-grecque-mythes-et-l%C3%A9gendes-1": {
            "title": "Mythologie grecque - Mythes et L\u00e9gendes 1...",
            "snippet": "Mythologie grecque - Mythes et L\u00e9gendes 1 Soutenez moi sur Tipeee: Abonnez-vous \u00e0 ma chaine: Facebook: Twitter:... From: Nota Bene Views: 140191 6991 ratings Time: 15:55 More in Education...",
            "date": "2014-12-01",
            "author_name": "Nota Bene",
            "categories": "mythologie,facebook,twitter",
            "tags": "nota,nota_bene,bene,chaine,moi,mythologie,grecque,mythes,l\u00e9gendes,soutenez,tipeee,abonnez,facebook,twitter,education",
            "recuweb_url": "http://fr.recuweb.com/twitter/youtube.com/2014/12/mythologie-grecque-mythes-et-l%C3%A9gendes-1",
            "resource_url": "http://gdata.youtube.com/feeds/base/videos?max-results=50&start-index=1&client=ytapi-youtube-search&v=2&q=mythologie%2Bmythologie&hl=fr-FR&lang=fr&lr=fr&orderby=relevance_lang_fr",
            "source_url": "http://youtube.com/watch?v=ELUfQQSUcEo&feature=youtube_gdata",
            "img_url": "http://img.youtube.com/vi/ELUfQQSUcEo/0.jpg"
        },
        "youtube.com/2014/11/les-dieux-nordiques-documentaire-en-fran%C3%A7ais-2014": {
            "title": "Les Dieux Nordiques documentaire en fran\u00e7ais 2014...",
            "snippet": "Les Dieux Nordiques documentaire en fran\u00e7ais 2014 La mythologie nordique est l'ensemble des mythes provenant d'Europe du Nord (plus particuli\u00e8rement de la Scandinavie et de l'Islande) \u00e0 la base du syst\u00e8me religieux polyth\u00e9iste pratiqu\u00e9...",
            "date": "2014-11-04",
            "author_name": "Jack Lance",
            "categories": "mythologie",
            "tags": "mythes,mythologie,mythologie-nordique,documentaire",
            "recuweb_url": "http://fr.recuweb.com/mythologie/youtube.com/2014/11/les-dieux-nordiques-documentaire-en-fran%C3%A7ais-2014",
            "resource_url": "http://gdata.youtube.com/feeds/base/videos?max-results=50&start-index=1&client=ytapi-youtube-search&v=2&q=mythologie&hl=fr-FR&lang=fr&lr=fr&orderby=relevance_lang_fr",
            "source_url": "http://youtube.com/watch?v=Uma4gn2axVs&feature=youtube_gdata",
            "img_url": "http://img.youtube.com/vi/Uma4gn2axVs/0.jpg"
        },
        "youtube.com/2014/10/la-gr%C3%A8ce-antique-l-ge-d-or-documentaire-fr": {
            "title": "La Gr\u00e8ce Antique L'ge d'or Documentaire Fr...",
            "snippet": "La Gr\u00e8ce Antique L'ge d'or Documentaire Fr L'ge d'or est un mythe qui appara\u00eet principalement dans la mythologie grecque puis la mythologie romaine (qui s'y r\u00e9f\u00e8re sous le nom de r\u00e8gne de Saturne). L'ge d'or fait partie... From: VideoBus Views:...",
            "date": "2014-10-23",
            "author_name": "VideoBus",
            "categories": "mythologie",
            "tags": "mythe,mythologie,grecque,documentaire",
            "recuweb_url": "http://fr.recuweb.com/mythologie/youtube.com/2014/10/la-gr%C3%A8ce-antique-l-ge-d-or-documentaire-fr",
            "resource_url": "http://gdata.youtube.com/feeds/base/videos?max-results=50&start-index=1&client=ytapi-youtube-search&v=2&q=mythologie%2Bmythologie&hl=fr-FR&lang=fr&lr=fr&orderby=relevance_lang_fr",
            "source_url": "http://youtube.com/watch?v=bYcli_7b_n8&feature=youtube_gdata",
            "img_url": "http://img.youtube.com/vi/bYcli_7b_n8/0.jpg"
        },
        "youtube.com/2014/09/les-minutes-mythologiques-ep-3-prom%C3%A9th%C3%A9e": {
            "title": "Les Minutes Mythologiques ep-3 Prom\u00e9th\u00e9e...",
            "snippet": "Les Minutes Mythologiques ep-3 Prom\u00e9th\u00e9e Pour le mois de Septembre Mr Mythologie pr\u00e9sente le mythe de Prom\u00e9th\u00e9e, p\u00e8re des Hommes. Mythe in\u00e9vitable de la cr\u00e9ation des hommes. Prochain \u00e9pisode en Octobre! Merci \u00e0 Gauvain,... From: Les...",
            "date": "2014-09-23",
            "author_name": "Les minutes Mythologiques",
            "categories": "mythologie",
            "tags": "cr\u00e9ation,mythe,mythologie",
            "recuweb_url": "http://fr.recuweb.com/mythologie/youtube.com/2014/09/les-minutes-mythologiques-ep-3-prom%C3%A9th%C3%A9e",
            "resource_url": "http://gdata.youtube.com/feeds/base/videos?max-results=50&start-index=1&client=ytapi-youtube-search&v=2&q=mythologie%2Bmythologie&hl=fr-FR&lang=fr&lr=fr&orderby=relevance_lang_fr",
            "source_url": "http://youtube.com/watch?v=QYYqtiAlVDA&feature=youtube_gdata",
            "img_url": "http://img.youtube.com/vi/QYYqtiAlVDA/0.jpg"
        },
        "dailymotion.com/2014/09/la-chronique-de-pierre-nuss-mythologie-mulhousienne": {
            "title": "La chronique de Pierre Nuss: la mythologie mulhousienne...",
            "snippet": "Sites webs/blogs, copiez cette vid\u00e9o avec le bouton \"code embed\"! Si vous voulez t\u00e9l\u00e9charger, allez sur. Tous les mercredis, retrouvez la chronique Patrimoine de Pierre Nuss. plus sur. Pour exploitation TV, droits r\u00e9serv\u00e9s, nous contacter sur:...",
            "date": "2014-09-12",
            "author_name": "Alsace20",
            "categories": "mythologie",
            "tags": "mythologie",
            "recuweb_url": "http://fr.recuweb.com/mythologie/dailymotion.com/2014/09/la-chronique-de-pierre-nuss-mythologie-mulhousienne",
            "resource_url": "http://www.dailymotion.com/rss/relevance/lang/fr/search/mythologie+mythologie/0?af=1",
            "source_url": "http://dailymotion.com/video/x25t5pj_la-chronique-de-pierre-nuss-la-mythologie-mulhousienne_creation",
            "img_url": "http://www.dailymotion.com/thumbnail/video/x25t5pj_la-chronique-de-pierre-nuss-la-mythologie-mulhousienne_creation"
        },
        "youtube.com/2014/08/pr%C3%A9sentation-de-la-chaine-un-coup-d-oeil-sur-mythologie-1": {
            "title": "Pr\u00e9sentation de la chaine Un Coup D'OEil sur la Mythologie 1 - Arceus...",
            "snippet": "Pr\u00e9sentation de la chaine Un Coup D'OEil sur la Mythologie 1 - Arceus Salut a tous c'est Dark Exagide et on se retrouve aujourd'hui pour ma premi\u00e8re vid\u00e9o! J'esp\u00e8re qu'elle vous plaira! Cha\u00eene du YouTuber qui a fait le montage avec tout les...",
            "date": "2014-08-03",
            "author_name": "Le Nostenfer Noir - Mythologie Pok\u00e9mon",
            "categories": "mythologie",
            "tags": "mythologie",
            "recuweb_url": "http://fr.recuweb.com/mythologie/youtube.com/2014/08/pr%C3%A9sentation-de-la-chaine-un-coup-d-oeil-sur-mythologie-1",
            "resource_url": "http://gdata.youtube.com/feeds/base/videos?max-results=50&start-index=1&client=ytapi-youtube-search&v=2&q=mythologie%2Bmythologie&hl=fr-FR&lang=fr&lr=fr&orderby=relevance_lang_fr",
            "source_url": "http://youtube.com/watch?v=aPJiMx0Ad0Y&feature=youtube_gdata",
            "img_url": "http://img.youtube.com/vi/aPJiMx0Ad0Y/0.jpg"
        },
        "youtube.com/2014/06/la-cr%C3%A9ation-du-monde-d-apr%C3%A8s-mythologie-egyptienne": {
            "title": "La Cr\u00e9ation du Monde d'apr\u00e8s la Mythologie Egyptienne...",
            "snippet": "La Cr\u00e9ation du Monde d'apr\u00e8s la Mythologie Egyptienne R\u00e9alis\u00e9 par la classe de 6\u00e8me E du Coll\u00e8ge Chantemerle de Corbeil-Essonne (91) en partenariat avec la MJC Fernand L\u00e9ger dans le cadre du dispositif \"Mieux r\u00e9ussir sa 6\u00e8me\" From: VIDEOMJC...",
            "date": "2014-06-11",
            "author_name": "VIDEOMJC CORBEIL",
            "categories": "mythologie",
            "tags": "mythologie,cr\u00e9ation",
            "recuweb_url": "http://fr.recuweb.com/mythologie/youtube.com/2014/06/la-cr%C3%A9ation-du-monde-d-apr%C3%A8s-mythologie-egyptienne",
            "resource_url": "http://gdata.youtube.com/feeds/base/videos?max-results=50&start-index=1&client=ytapi-youtube-search&v=2&q=mythologie&hl=fr-FR&lang=fr&lr=fr&orderby=relevance_lang_fr",
            "source_url": "http://youtube.com/watch?v=kiS0I1cj7qM&feature=youtube_gdata",
            "img_url": "http://img.youtube.com/vi/kiS0I1cj7qM/0.jpg"
        },
        "dailymotion.com/2014/05/the-order-1886-histoire-et-mythologie": {
            "title": "The Order 1886 - Histoire et Mythologie...",
            "snippet": "The Order 1886 (PlayStation 4) - Histoire et MythologieAuthor: GamekultTags: Carnet de d\u00e9veloppeur Posted: 27 May 2014Rating:: 0...",
            "date": "2014-05-27",
            "author_name": "Gamekult",
            "categories": "mythologie,playstation",
            "tags": "mythologie",
            "recuweb_url": "http://fr.recuweb.com/playstation/dailymotion.com/2014/05/the-order-1886-histoire-et-mythologie",
            "resource_url": "http://www.dailymotion.com/rss/relevance/lang/fr/search/mythologie+mythologie/0?af=1",
            "source_url": "http://dailymotion.com/video/x1x2v4r_the-order-1886-histoire-et-mythologie_videogames",
            "img_url": "http://www.dailymotion.com/thumbnail/video/x1x2v4r_the-order-1886-histoire-et-mythologie_videogames"
        }
    }
}