{
    "meta": {
        "portal_name": "pagerank",
        "language": "fr",
        "updated": "20150503"
    },
    "schema": {
        "html:portal": "http://fr.recuweb.com/pagerank/",
        "graph:videos": "http://fr.recuweb.com/graph/v1.0/pagerank/pagerank/vid%C3%A9os.json",
        "graph:news": "http://fr.recuweb.com/graph/v1.0/pagerank/pagerank/actualit%C3%A9s.json",
        "graph:blogs": "http://fr.recuweb.com/graph/v1.0/pagerank/pagerank/blogs.json"
    },
    "items": {
        "hypertexte.fr/2015/01/google-pagerank-c-est-fini-hypertexte": {
            "title": "Google PageRank: c'est fini! Hypertexte...",
            "snippet": "L'indicateur PageRank de Google a \u00e9t\u00e9 abandonn\u00e9. D\u00e9sormais, la qualit\u00e9 (et non plus le nombre seul) des liens compte plus que tout.",
            "date": "2015-01-26",
            "author_name": "Pascal Maupas",
            "categories": "google,pagerank",
            "tags": "google,google_pagerank,pagerank",
            "recuweb_url": "http://fr.recuweb.com/pagerank/hypertexte.fr/2015/01/google-pagerank-c-est-fini-hypertexte",
            "resource_url": "http://www.google.com/search?q=pagerank%2Bpagerank&tbm=blg&output=atom&start=0&hl=fr&lr=lang_fr&nord=1",
            "source_url": "http://hypertexte.fr/blog/google-pagerank-cest-fini/"
        },
        "infowebmaster.fr/2012/05/pagerank-sculpting-explications-infowebmaster": {
            "title": "PageRank Sculpting: Explications - InfoWebMaster...",
            "snippet": "Le PageRank Sculpting est une optimisation utilis\u00e9e en r\u00e9f\u00e9rencement pour am\u00e9liorer la fa\u00e7on dont le PageRank circule entre les pages.",
            "date": "2012-05-17",
            "author_name": "inconnu",
            "categories": "pagerank",
            "tags": "am\u00e9liorer,pagerank,r\u00e9f\u00e9rencement",
            "recuweb_url": "http://fr.recuweb.com/pagerank/infowebmaster.fr/2012/05/pagerank-sculpting-explications-infowebmaster",
            "resource_url": "http://www.google.com/search?q=pagerank&tbm=blg&output=atom&start=0&hl=fr&lr=lang_fr&nord=1",
            "source_url": "http://infowebmaster.fr/75,news-pagerank-sculpting-explications.html"
        },
        "webmaster-hub.com/2012/05/comment-am%C3%A9liorer-le-pagerank-techniques-de-r%C3%A9f%C3%A9rencement": {
            "title": "Comment am\u00e9liorer le PageRank? - Techniques de R\u00e9f\u00e9rencement...",
            "snippet": "J'aimerai savoir les actions possibles et n\u00e9cessaires pour am\u00e9liorer le PageRank de mon site? et comment faire pour obtenir des BACKLINKS? Modifi\u00e9 par Branco, 17 mai 2012 - 15:23. 0. Votre confort est notre engagement...",
            "date": "2012-05-17",
            "author_name": "inconnu",
            "categories": "pagerank",
            "tags": "site,am\u00e9liorer,pagerank,r\u00e9f\u00e9rencement",
            "recuweb_url": "http://fr.recuweb.com/pagerank/webmaster-hub.com/2012/05/comment-am%C3%A9liorer-le-pagerank-techniques-de-r%C3%A9f%C3%A9rencement",
            "resource_url": "http://www.google.com/search?q=pagerank%2Bpagerank&tbm=blg&output=atom&start=0&hl=fr&lr=lang_fr&nord=1",
            "source_url": "http://webmaster-hub.com/topic/53439-comment-ameliorer-le-pagerank/"
        },
        "edicy.com/2010/04/qu-est-ce-que-google-pagerank-edicy-blog": {
            "title": "Qu'est ce que Google PageRank? Edicy blog...",
            "snippet": "Google PageRank est le plus important des m\u00e9canismes sous-jacents du moteur de recherche Google. En effet, Google donne automatiquement un meilleur placement dans la liste de r\u00e9sultats aux sites qui on un bon score PageRank.",
            "date": "2010-04-17",
            "author_name": "T\u00f5nu Runnel",
            "categories": "moteur-de-recherche,google,pagerank",
            "tags": "automatiquement,google,google_pagerank,pagerank,important,sites",
            "recuweb_url": "http://fr.recuweb.com/pagerank/edicy.com/2010/04/qu-est-ce-que-google-pagerank-edicy-blog",
            "resource_url": "http://www.google.com/search?q=pagerank%2Bpagerank&tbm=blg&output=atom&start=0&hl=fr&lr=lang_fr&nord=1",
            "source_url": "http://edicy.com/blog-fr/quest-ce-que-google-pagerank"
        }
    }
}