{
    "meta": {
        "portal_name": "hockey",
        "language": "fr"
    },
    "schema": {
        "html:portal": "http://fr.recuweb.com/hockey/",
        "graph:videos": "http://fr.recuweb.com/graph/v1.0/hockey/hockey/vid%C3%A9os.json",
        "graph:news": "http://fr.recuweb.com/graph/v1.0/hockey/hockey/actualit%C3%A9s.json",
        "graph:blogs": "http://fr.recuweb.com/graph/v1.0/hockey/hockey/blogs.json"
    },
    "items": {
        "blogues.lapresse.ca/2015/04/par-o%C3%B9-commencer-mathias-brunet-blogues": {
            "title": "Par o\u00f9 commencer???Mathias Brunet - Blogues -...",
            "snippet": "Je pense que ni Dubnyk ni Price devraient obtenir le Hart car ils occupent la position de loin la plus importante au hockey. \u00c7a biaise les choses. Mais si Price est candidat pour le Hart, Dubnyk l'est tout autant, et Dubnyk l'a eu...",
            "date": "2015-04-10",
            "author_name": "rondellelibre",
            "categories": "hockey",
            "tags": "autant,position,hockey",
            "recuweb_url": "http://fr.recuweb.com/hockey/blogues.lapresse.ca/2015/04/par-o%C3%B9-commencer-mathias-brunet-blogues",
            "resource_url": "http://www.google.com/search?q=hockey%2Bhockey&tbm=blg&output=atom&start=0&hl=fr&lr=lang_fr&nord=1",
            "source_url": "http://blogues.lapresse.ca/lnh/2015/04/10/par-ou-commencer/"
        },
        "lemedia05.com/2015/04/gap-les-champions-de-france-hockey-re%C3%A7us-avec-la-coupe": {
            "title": "Gap: les champions de France de hockey re\u00e7us avec la coupe...",
            "snippet": "La question \u00e9pineuse des heures de glace suppl\u00e9mentaires pour le hockey mineur, qui avait \u00e9t\u00e9 \u00e9voqu\u00e9e lors de la conf\u00e9rence de presse du club mardi matin, n'a pas davantage \u00e9t\u00e9 abord\u00e9e. Dany Galland, adjoint aux...",
            "date": "2015-04-09",
            "author_name": "Jean-Christophe Sarrazin",
            "categories": "hockey",
            "tags": "dany,coupe,champions,gap,france,hockey,glace,mineur,\u00e9t\u00e9,lors,club",
            "recuweb_url": "http://fr.recuweb.com/hockey/lemedia05.com/2015/04/gap-les-champions-de-france-hockey-re%C3%A7us-avec-la-coupe",
            "resource_url": "http://www.google.com/search?q=hockey%2Bhockey&tbm=blg&output=atom&start=0&hl=fr&lr=lang_fr&nord=1",
            "source_url": "http://lemedia05.com/2015/21086/gap-les-champions-de-france-de-hockey-recus-avec-la-coupe-magnus-a-lhotel-de-ville/"
        },
        "25stanley.com/2015/04/les-9-gros-dramas-de-la-s%C3%A9rie-hockey-wives-25stanley": {
            "title": "Les 9 gros dramas de la s\u00e9rie Hockey Wives 25stanley...",
            "snippet": "Mercredi soir \u00e9tait diffus\u00e9 le 4e \u00e9pisode de la s\u00e9rie Hockey Wives. Compte tenu de l'angle \u00e9ditorial du 25stanley, je dois admettre que j&.",
            "date": "2015-04-09",
            "author_name": "jtutah",
            "categories": "hockey",
            "tags": "tenu,s\u00e9rie,\u00e9tait,hockey,mercredi,compte",
            "recuweb_url": "http://fr.recuweb.com/hockey/25stanley.com/2015/04/les-9-gros-dramas-de-la-s%C3%A9rie-hockey-wives-25stanley",
            "resource_url": "http://www.google.com/search?q=hockey%2Bhockey&tbm=blg&output=atom&start=0&hl=fr&lr=lang_fr&nord=1",
            "source_url": "http://25stanley.com/les-9-gros-dramas-de-la-serie-hockey-wives.html"
        },
        "lemedia05.com/2015/04/hockey-les-rapaces-de-gap-l%C3%A8vent-un-premier-coin-voile": {
            "title": "Hockey: les Rapaces de Gap l\u00e8vent un premier coin de voile sur la...",
            "snippet": "Avant de s'envoler pour Barcelone, ce mercredi, pour y pr\u00e9parer l'\u00e9quipe nationale espagnole en vue des championnats du monde en Islande, l'entra\u00eeneur des Rapaces de Gap, Luciano Basile, est revenu sur le bilan de la...",
            "date": "2015-04-07",
            "author_name": "Jean-Christophe Sarrazin",
            "categories": "hockey",
            "tags": "nationale,mercredi,premier,hockey,gap,\u00e9quipe",
            "recuweb_url": "http://fr.recuweb.com/hockey/lemedia05.com/2015/04/hockey-les-rapaces-de-gap-l%C3%A8vent-un-premier-coin-voile",
            "resource_url": "http://www.google.com/search?q=hockey%2Bhockey&tbm=blg&output=atom&start=0&hl=fr&lr=lang_fr&nord=1",
            "source_url": "http://lemedia05.com/2015/21006/hockey-les-rapaces-de-gap-levent-un-premier-coin-de-voile-sur-la-saison-2015-2016/"
        },
        "dijon-sportnews.fr/2015/03/hockey-r%C3%A9sultat-du-week-end-28-29-mars-pour-les-jeunes": {
            "title": "Hockey: r\u00e9sultat du week-end du 28-29 mars pour les jeunes du DHC...",
            "snippet": "Voici les r\u00e9sultats des cat\u00e9gories jeunes du Dijon Hockey Club pour le week-end des 28-29 mars. Cat\u00e9gorie U11 \u00e9quipe B. Longtemps ind\u00e9cis, le duel s'est finalement conclu par la victoire des Ducs dans le dernier tiers.",
            "date": "2015-03-30",
            "author_name": "Nicolas G.",
            "categories": "hockey",
            "tags": "victoire,club,cat\u00e9gorie,hockey,voici,\u00e9quipe",
            "recuweb_url": "http://fr.recuweb.com/hockey/dijon-sportnews.fr/2015/03/hockey-r%C3%A9sultat-du-week-end-28-29-mars-pour-les-jeunes",
            "resource_url": "http://www.google.com/search?q=hockey&tbm=blg&output=atom&start=0&hl=fr&lr=lang_fr&nord=1",
            "source_url": "http://dijon-sportnews.fr/2015/03/30/hockey-resultat-du-weekend-du-28-29-mars-pour-les-jeunes-du-dhc/106752/"
        },
        "blogues.lapresse.ca/2015/03/lhjmq-les-pr%C3%A9dictions-de-fran%C3%A7ois-parenteaule-blogue-hockey": {
            "title": "LHJMQ: les pr\u00e9dictions de Fran\u00e7ois ParenteauLe blogue de hockey...",
            "snippet": "Voici mes pr\u00e9dictions pour la vraie saison dans la LHJMQ. Et vous, quelles sont les v\u00f4tres? Rimouski (1) contre Victoriaville (16) C'est la seule s\u00e9rie que je vois se terminer en quatre matchs. L'Oc\u00e9anic, la meilleure \u00e9quipe...",
            "date": "2015-03-26",
            "author_name": "Frank_Parenteau",
            "categories": "hockey",
            "tags": "s\u00e9rie,saison,fran\u00e7ois,hockey,voici,contre,matchs,\u00e9quipe",
            "recuweb_url": "http://fr.recuweb.com/hockey/blogues.lapresse.ca/2015/03/lhjmq-les-pr%C3%A9dictions-de-fran%C3%A7ois-parenteaule-blogue-hockey",
            "resource_url": "http://www.google.com/search?q=hockey&tbm=blg&output=atom&start=0&hl=fr&lr=lang_fr&nord=1",
            "source_url": "http://blogues.lapresse.ca/hockey-junior/2015/03/26/lhjmq-les-predictions-de-francois-parenteau/"
        },
        "sopdow5570.wordpress.com/2015/03/les-batailles-au-hockey-et-mises-en-%C3%A9chec-sont-elles-vraiment": {
            "title": "Les batailles au hockey et les mises en \u00e9chec sont-elles vraiment une bonne id\u00e9e?",
            "snippet": "Par: Sophie Downer Y a-t-il une grande fr\u00e9quence de blessure dans le sport que vous pratiquez? Y a-t-il un plus grand risque de blessure dans les sports d'hiver...",
            "date": "2015-03-25",
            "author_name": "sopdow5570",
            "categories": "sport,hockey",
            "tags": "grand,sports,hockey",
            "recuweb_url": "http://fr.recuweb.com/hockey/sopdow5570.wordpress.com/2015/03/les-batailles-au-hockey-et-mises-en-%C3%A9chec-sont-elles-vraiment",
            "resource_url": "http://fr.search.wordpress.com/?q=hockey%2Bhockey&f=feed&page=1",
            "source_url": "http://sopdow5570.wordpress.com/2015/03/25/les-batailles-au-hockey-et-les-mises-en-echec-sont-elles-vraiment-une-bonne-idee/"
        },
        "sudouest.fr/2015/03/hockey-d1-les-dates-des-finales-entre-l-hormadi-d-anglet": {
            "title": "Hockey (D1): les dates des finales entre l'Hormadi d'Anglet et les...",
            "snippet": "Compte-tenu de l'indisponibilit\u00e9 de la patinoire bordelaise dimanche, et du refus d'Anglet d'avancer le premier match au vendredi, l'Hormadi accueillera le deuxi\u00e8me match de la finale de Division 1...",
            "date": "2015-03-23",
            "author_name": "inconnu",
            "categories": "hockey",
            "tags": "premier,dimanche,tenu,finales,finale,hockey,compte,match",
            "recuweb_url": "http://fr.recuweb.com/hockey/sudouest.fr/2015/03/hockey-d1-les-dates-des-finales-entre-l-hormadi-d-anglet",
            "resource_url": "http://www.google.com/search?q=hockey&tbm=blg&output=atom&start=0&hl=fr&lr=lang_fr&nord=1",
            "source_url": "http://sudouest.fr/2015/03/23/hockey-d1-les-dates-des-finales-entre-l-hormadi-d-anglet-et-les-boxers-de-bordeaux-connues-1868287-4018.php"
        },
        "footvshockey.wordpress.com/2015/02/foot-v-hockey": {
            "title": "Foot v Hockey...",
            "snippet": "Beaucoup d'enfant et d'adultes au Canada jouent foot et a l'hockey. Moi personnellement je prefere le foot et j'ai mes raisons. Ma premiere raison est parce que c'est...",
            "date": "2015-02-17",
            "author_name": "pbn12",
            "categories": "hockey",
            "tags": "hockey,canada",
            "recuweb_url": "http://fr.recuweb.com/hockey/footvshockey.wordpress.com/2015/02/foot-v-hockey",
            "resource_url": "http://fr.search.wordpress.com/?q=hockey%2Bhockey&f=feed&page=1",
            "source_url": "http://footvshockey.wordpress.com/2015/02/17/foot-v-hockey/"
        },
        "sainte-marie.ca/2015/01/r%C3%A9gionaux-de-hockey-mineur-ville-sainte-marie": {
            "title": "R\u00e9gionaux de hockey mineur Ville de Sainte-Marie...",
            "snippet": "Le groupe Ledor Assurances sera le partenaire de Hockey Qu\u00e9bec-Chaudi\u00e8re-Appalaches pour les trois prochaines ann\u00e9es des finales r\u00e9gionales simple lettre, de la r\u00e9gion de Qu\u00e9bec-Chaudi\u00e8re-Appalaches. Les finales...",
            "date": "2015-01-04",
            "author_name": "Ville Sainte-Marie",
            "categories": "hockey,assurance",
            "tags": "finales,hockey,qu\u00e9bec,partenaire,mineur,groupe",
            "recuweb_url": "http://fr.recuweb.com/assurance/sainte-marie.ca/2015/01/r%C3%A9gionaux-de-hockey-mineur-ville-sainte-marie",
            "resource_url": "http://www.google.com/search?q=hockey%2Bhockey&tbm=blg&output=atom&start=0&hl=fr&lr=lang_fr&nord=1",
            "source_url": "http://sainte-marie.ca/2015/04/regionaux-de-hockey-mineur/"
        }
    }
}