{
    "meta": {
        "portal_name": "surf",
        "language": "fr",
        "updated": "20150429"
    },
    "schema": {
        "html:portal": "http://fr.recuweb.com/surf/",
        "graph:videos": "http://fr.recuweb.com/graph/v1.0/surf/surf/vid%C3%A9os.json",
        "graph:news": "http://fr.recuweb.com/graph/v1.0/surf/surf/actualit%C3%A9s.json",
        "graph:blogs": "http://fr.recuweb.com/graph/v1.0/surf/surf/blogs.json"
    },
    "items": {
        "surf.blogs.sudouest.fr/2015/04/oakley-lowers-pro-le-circuit-qs-retrouve-trestles-plan%C3%A8te-surf": {
            "title": "Oakley Lowers Pro: le circuit QS retrouve Trestles: Plan\u00e8te Surf...",
            "snippet": "MATEIA HIQUILY (5e): Le mieux class\u00e9 des surfeurs tricolores au classement qualificatif reste sur une petite d\u00e9ception, au Papara Surf Festival (QS 1000), o\u00f9 le Tahitien a abandonn\u00e9 son titre gagn\u00e9 l'an dernier en se faisant...",
            "date": "2015-04-27",
            "author_name": "Plan\u00e8te Surf",
            "categories": "surf",
            "tags": "dernier,o\u00f9,surf,surfeurs,surfeurs-tricolores,tricolores,reste,petite,plan\u00e8te,plan\u00e8te_surf,circuit,pro,retrouve",
            "recuweb_url": "http://fr.recuweb.com/surf/surf.blogs.sudouest.fr/2015/04/oakley-lowers-pro-le-circuit-qs-retrouve-trestles-plan%C3%A8te-surf",
            "resource_url": "http://www.google.com/search?q=surf%2Bsurf&tbm=blg&output=atom&start=0&hl=fr&lr=lang_fr&nord=1",
            "source_url": "http://surf.blogs.sudouest.fr/archive/2015/04/26/oakley-lowers-pro-le-circuit-qs-retrouve-trestles.html"
        },
        "zejournal.info/2015/04/un-costume-combinaison-de-surf-commercialis%C3%A9-au-japon": {
            "title": "Un costume-combinaison de surf commercialis\u00e9 au Japon...",
            "snippet": "En association avec l'agence publicitaire nipponne TBWAHAKUHODO, Quicksilver a cr\u00e9\u00e9 et commercialis\u00e9 une combinaison de surf reprenant la coupe d'un costume 2 pi\u00e8ces, pour homme. Intitul\u00e9 The True Wetsuit,...",
            "date": "2015-04-27",
            "author_name": "Mathias",
            "categories": "surf",
            "tags": "surf",
            "recuweb_url": "http://fr.recuweb.com/surf/zejournal.info/2015/04/un-costume-combinaison-de-surf-commercialis%C3%A9-au-japon",
            "resource_url": "http://www.google.com/search?q=surf%2Bsurf&tbm=blg&output=atom&start=0&hl=fr&lr=lang_fr&nord=1",
            "source_url": "http://zejournal.info/videos-insolites/12612-costume-combinaison-de-surf-quicksilver-japon"
        },
        "adonnante.com/2015/04/martinique-surf-pro-2015-joshua-moniz-l-espoir-qui-monte": {
            "title": "Martinique Surf Pro PRO 2015 - Joshua Moniz, l'espoir qui monte...",
            "snippet": "C'est finalement l'Hawa\u00efen Joshua Moniz (18 ans) qui a remport\u00e9 le Martinique Surf Pro, l'unique \u00e9preuve carib\u00e9enne des World Surf League Qualification Series (QS) en 2015.",
            "date": "2015-04-25",
            "author_name": "gmo",
            "categories": "surf",
            "tags": "surf,martinique,martinique_surf,martinique_surf_pro,surf_pro,pro,finalement,joshua,joshua_moniz,moniz",
            "recuweb_url": "http://fr.recuweb.com/surf/adonnante.com/2015/04/martinique-surf-pro-2015-joshua-moniz-l-espoir-qui-monte",
            "resource_url": "http://www.google.com/search?q=surf%2Bsurf&tbm=blg&output=atom&start=0&hl=fr&lr=lang_fr&nord=1",
            "source_url": "http://adonnante.com/32651-h2o-surf-martinique-surf-pro-pro-2015-montee-en-pression-2/"
        },
        "surf.blogs.sudouest.fr/2015/04/martinique-surf-pro-les-2-premiers-jours-en-images-plan%C3%A8te": {
            "title": "Martinique Surf Pro: les 2 premiers jours en images: Plan\u00e8te Surf...",
            "snippet": "Douze surfeurs tricolores sur les 23 au d\u00e9part en d\u00e9coudront au 3e tour o\u00f9 les principales t\u00eates de s\u00e9rie dont Pierson, Toyon, Distinguin feront leur entr\u00e9e. martinique surf pro 2015 Tom Cloarec file au 3e tour... Photo...",
            "date": "2015-04-22",
            "author_name": "Plan\u00e8te Surf",
            "categories": "surf",
            "tags": "cloarec,o\u00f9,surfeurs,surfeurs-tricolores,tricolores,plan\u00e8te,plan\u00e8te_surf,surf,images,martinique,martinique_surf,martinique_surf_pro,surf_pro,pro",
            "recuweb_url": "http://fr.recuweb.com/surf/surf.blogs.sudouest.fr/2015/04/martinique-surf-pro-les-2-premiers-jours-en-images-plan%C3%A8te",
            "resource_url": "http://www.google.com/search?q=surf%2Bsurf&tbm=blg&output=atom&start=0&hl=fr&lr=lang_fr&nord=1",
            "source_url": "http://surf.blogs.sudouest.fr/archive/2015/04/22/martinique-surf-pro-les-2-premiers-jours-en-images-1035725.html"
        },
        "laitfraisevidesressing.wordpress.com/2015/03/skate-&-surf": {
            "title": "Skate & Surf...",
            "snippet": "Tumblr: Old School Life 1976 Tenu par mon copain, passionn\u00e9 de skate, de surf, des Doors et de Pink Floyd, vous y trouverez des images des plus grands...",
            "date": "2015-03-27",
            "author_name": "laitfraisevidedressing",
            "categories": "surf,tumblr",
            "tags": "images,surf",
            "recuweb_url": "http://fr.recuweb.com/tumblr/laitfraisevidesressing.wordpress.com/2015/03/skate-&-surf",
            "resource_url": "http://fr.search.wordpress.com/?q=surf%2Bsurf&f=feed&page=1",
            "source_url": "http://laitfraisevidesressing.wordpress.com/2015/03/27/old-school-life-1976-skate-surf/"
        },
        "vivreetvoyagerenvoilier.blogspot.com/2015/03/iles-san-andres-et-providencia": {
            "title": "Iles San Andres et Providencia...",
            "snippet": "Ces deux iles bien quau large du Nicaragua, sont Colombiennes, San Andres tres peupl\u00e9e et avec beaucoup de tourisme, avec aussi les structures pour, grand aeroport, hotels, bars restos et ville, activit\u00e9es de kit surf, surf, plong\u00e9e. Jai bien...",
            "date": "2015-03-11",
            "author_name": "Johnny Zeisner",
            "categories": "surf",
            "tags": "grand,deux,surf",
            "recuweb_url": "http://fr.recuweb.com/surf/vivreetvoyagerenvoilier.blogspot.com/2015/03/iles-san-andres-et-providencia",
            "resource_url": "http://www.icerocket.com/search?tab=blog&q=surf%2Bsurf&rss=1&lng=fr",
            "source_url": "http://vivreetvoyagerenvoilier.blogspot.com/2015/03/iles-san-andres-et-providencia.html"
        },
        "actusportextreme.com/2015/03/kelly-slater-sa-carri%C3%A8re-wct-en-chiffres-et-records": {
            "title": "Kelly Slater: Sa carri\u00e8re WCT en chiffres et en records...",
            "snippet": "Kelly Slater, ic\u00f4ne vivante du surf, a d\u00e9but\u00e9 le 28 f\u00e9vrier une nouvelle saison dans le circuit \u00e9lite. L'occasion de revenir sur les moments forts de la carri\u00e8re []...",
            "date": "2015-03-01",
            "author_name": "nicolasarquin",
            "categories": "surf",
            "tags": "occasion,saison,circuit,surf",
            "recuweb_url": "http://fr.recuweb.com/surf/actusportextreme.com/2015/03/kelly-slater-sa-carri%C3%A8re-wct-en-chiffres-et-records",
            "resource_url": "http://fr.search.wordpress.com/?q=surf%2Bsurf&f=feed&page=1",
            "source_url": "http://actusportextreme.com/2015/03/01/kelly-slater-sa-carriere-wct-en-chiffres-et-en-records/"
        },
        "cocogwada.wordpress.com/2015/02/les-sessions-surf": {
            "title": "les sessions SURF!!",
            "snippet": "R\u00e9mi a d\u00e9cid\u00e9 cette ann\u00e9e de prendre des cours de surf et franchement il se d\u00e9brouille plut\u00f4t tr\u00e8s bien!!!... En m\u00eame temps, j'allais pas vous dire...",
            "date": "2015-02-01",
            "author_name": "cocogwada",
            "categories": "surf",
            "tags": "surf",
            "recuweb_url": "http://fr.recuweb.com/surf/cocogwada.wordpress.com/2015/02/les-sessions-surf",
            "resource_url": "http://fr.search.wordpress.com/?q=surf%2Bsurf&f=feed&page=1",
            "source_url": "http://cocogwada.wordpress.com/2015/02/01/les-sessions-surf/"
        },
        "cotentinois3.wordpress.com/2015/01/surf-in-sciotot": {
            "title": "Surf'in Sciotot...",
            "snippet": "Dimanche dernier, grand bol d'air en compagnie d'Ilana sur la plage de Sciotot. Une envie d'essayer sa nouvelle planche pour notre petite surfeuse et l'occasion de faire quelques []...",
            "date": "2015-01-12",
            "author_name": "cotentinois",
            "categories": "surf",
            "tags": "occasion,planche,petite,grand,surf,dernier",
            "recuweb_url": "http://fr.recuweb.com/surf/cotentinois3.wordpress.com/2015/01/surf-in-sciotot",
            "resource_url": "http://fr.search.wordpress.com/?q=surf%2Bsurf&f=feed&page=1",
            "source_url": "http://cotentinois3.wordpress.com/2015/01/12/surfin-sciotot/"
        }
    }
}